{"stem":"compon","instances":[{"docUri":"librarium\/For_my_Gods_and_Emperor.html","score":1,"contexts":[{"form":"components","weight":"1","pos":493,"context":"...and in the wilderness, gathering herbs and potion <mark>components<\/mark>. They should avoid trouble where possible, and...","fid":"content"}]},{"docUri":"librarium\/Vivec_and_Mephala.html","score":1,"contexts":[{"form":"components","weight":"1","pos":373,"context":"...with the hidden aspects of Vivec, the darker <mark>components<\/mark> of violence, lust, and conspiracy associated the...","fid":"content"}]}]}