{"stem":"differ","instances":[{"docUri":"librarium\/For_my_Gods_and_Emperor.html","score":2,"contexts":[{"form":"different","weight":"1","pos":130,"context":"...and virtuous life. Each of the Nine represents <mark>different<\/mark> aspects of life, and how it should be...","fid":"content"},{"form":"different","weight":"1","pos":681,"context":"...Redoran and the Morag Tong, and honors their <mark>different<\/mark> but noble conceptions of Divine Inspiration.","fid":"content"}]},{"docUri":"librarium\/Vampires_of_Vvardenfell.html","score":2,"contexts":[{"form":"differ","weight":"1","pos":169,"context":"...Vvardenfell's three known bloodlines <mark>differ<\/mark> greatly in their approach to prey. The Quarra...","fid":"content"},{"form":"different","weight":"1","pos":353,"context":"...upon the corpse of a defeated foe. Several <mark>different<\/mark> versions of this story exist, with the foe...","fid":"content"}]},{"docUri":"librarium\/Guide_to_Vvardenfell.html","score":1,"contexts":[{"form":"different","weight":"1","pos":124,"context":"...features. Scholars have based their classifications on the <mark>different<\/mark> types of land described by the native Ashlanders,...","fid":"content"}]},{"docUri":"librarium\/Reflections_on_Cult_Worship.html","score":1,"contexts":[{"form":"differences","weight":"1","pos":263,"context":"The <mark>differences<\/mark> in religious temperament between Heartlanders and Morrowind Dunmer accounts...","fid":"content"}]},{"docUri":"librarium\/The_Four_Suitors_of_Benitah.html","score":1,"contexts":[{"form":"different","weight":"1","pos":61,"context":"...salary, he suddenly found himself on a very <mark>different<\/mark> kind of society, one that he had been...","fid":"content","in":["ssCtx5"]}]},{"docUri":"librarium\/The_Prayers_of_Baranat.html","score":1,"contexts":[{"form":"different","weight":"1","pos":124,"context":"...Genevrah personally. Each of his brothers guarded a <mark>different<\/mark> post along the valley -- Baranat would have to...","fid":"content"}]}]}