{"stem":"dishonor","instances":[{"docUri":"librarium\/Fellowship_of_the_Temple.html","score":1,"contexts":[{"form":"dishonor","weight":"1","pos":208,"context":"...transgress against your brothers or sisters, and never <mark>dishonor<\/mark> your house or your ancestors. Serve and protect...","fid":"content"}]},{"docUri":"librarium\/The_Pilgrim's_Path.html","score":1,"contexts":[{"form":"dishonor","weight":"1","pos":312,"context":"...own silver longsword to the Daedra Lord rather than <mark>dishonor<\/mark> himself by fighting an unarmed foe. This so...","fid":"content"}]}]}