{"stem":"forg","instances":[{"docUri":"librarium\/the_book_of_dawn_n_dusk.html","score":2,"contexts":[{"form":"Forge","weight":"1","pos":134,"context":"<mark>Forge<\/mark> a keen Faith in the crucible of suffering....","fid":"content"},{"form":"Forge","weight":"1","pos":226,"context":"<mark>Forge<\/mark> Darkness into Light.","fid":"content"}]},{"docUri":"librarium\/Hanins_wake.html","score":1,"contexts":[{"form":"Forge","weight":"1","pos":46,"context":"...Even Hilbongard and Dorach Gusal were lured from their <mark>Forge<\/mark>, and for a time the Fires of Anudnabia...","fid":"content","in":["ssCtx5"]}]},{"docUri":"librarium\/Saryonis_Sermons_Manuscript.html","score":1,"contexts":[{"form":"Forge","weight":"1","pos":36,"context":"<mark>Forge<\/mark> a keen Faith in the crucible of suffering....","fid":"content"}]},{"docUri":"librarium\/Tal_Marog_Kers_Researches.html","score":1,"contexts":[{"form":"forged","weight":"1","pos":316,"context":"...instance, the Armor of the Savior's Hide, <mark>forged<\/mark> by Malacath -- are sufficient to protect a mortal...","fid":"content"}]}]}