{"stem":"hail","instances":[{"docUri":"librarium\/buyn_game_EX.html","score":1,"contexts":[{"form":"hail","weight":"1","pos":205,"context":"...prejudices of the region. In Morrowind where I <mark>hail<\/mark> from, for example, Argonians are viewed with a...","fid":"content"}]},{"docUri":"librarium\/morrowind_msg_Dagoth_Ur.html","score":1,"contexts":[{"form":"Hail","weight":"1","pos":15,"context":" Lord , <mark>Hail<\/mark>  My Lord, Friend, and Companion ","fid":"content","in":["ssCtx5"]}]},{"docUri":"librarium\/Realizations_of_Acrobacy.html","score":1,"contexts":[{"form":"hails","weight":"1","pos":183,"context":"...\"Master Senyndie? Ah, Mighty Gothren, she <mark>hails<\/mark> from the Alik'r Desert of Hammerfell where she won...","fid":"content"}]},{"docUri":"librarium\/silence.html","score":1,"contexts":[{"form":"hail","weight":"1","pos":66,"context":"...he said, raising a glass of . “I <mark>hail<\/mark> from the region of Ghostgate which is how I...","fid":"content","in":["ssCtx5"]}]}]}