{"stem":"held","instances":[{"docUri":"librarium\/Blasphemous_Revenants.html","score":1,"contexts":[{"form":"held","weight":"1","pos":125,"context":"...out of it, but between worlds they linger, <mark>held<\/mark> to the hearth and tomb by blood and loyalty...","fid":"content"}]},{"docUri":"librarium\/The_Four_Suitors_of_Benitah.html","score":1,"contexts":[{"form":"held","weight":"1","pos":202,"context":"...the lady's husband was not very well. Oin <mark>held<\/mark> back his happiness and continued on his errands....","fid":"content"}]},{"docUri":"librarium\/The_Prayers_of_Baranat.html","score":1,"contexts":[{"form":"held","weight":"1","pos":30,"context":"...When the Lady  was kidnapped from her estate and <mark>held<\/mark> for ransom, her mother sent word out that...","fid":"content","in":["ssCtx5"]}]},{"docUri":"librarium\/The_Real_Nerevar.html","score":1,"contexts":[{"form":"held","weight":"1","pos":84,"context":"...invited Orc and Nord clans as allies, and <mark>held<\/mark> northwest Morrowind, while Nerevar mustered the other Houses...","fid":"content"}]},{"docUri":"librarium\/Unnamed_Book.html","score":1,"contexts":[{"form":"held","weight":"1","pos":534,"context":"...designed compartments in his tunic's sleeves, where they <mark>held<\/mark> fast with no jingling or unusual bulges. \"We'll...","fid":"content"}]}]}