{"stem":"lost","instances":[{"docUri":"librarium\/Guide_to_Aldruhn.html","score":1,"contexts":[{"form":"lost","weight":"1","pos":338,"context":"...sidepaths; watch for signposts, or you'll get <mark>lost<\/mark>. The silt strider port is along the western...","fid":"content"}]},{"docUri":"librarium\/starlovers_log.html","score":1,"contexts":[{"form":"lost","weight":"1","pos":112,"context":"...with Dragonne Papré. Hope for the living is <mark>lost<\/mark>. My name is Samar Starlover. Tell my...","fid":"content"}]},{"docUri":"librarium\/The_Alchemists_Formulary.html","score":1,"contexts":[{"form":"lost","weight":"1","pos":168,"context":"...everywhere in Morrowind; the smaller eggs retain properties <mark>lost<\/mark> in later states of gestation. chokeweed is a...","fid":"content","in":["ssCtx5"]}]},{"docUri":"librarium\/The_Pilgrim's_Path.html","score":1,"contexts":[{"form":"lost","weight":"1","pos":362,"context":"...a scroll of ALMSIVI Intervention in case they get <mark>lost<\/mark>. The Dremora Krazzt is found in the center...","fid":"content"}]},{"docUri":"librarium\/The_Real_Nerevar.html","score":1,"contexts":[{"form":"lost","weight":"1","pos":124,"context":"...was killed in the battle, and his ring <mark>lost<\/mark>, but Nerevar's alliance survives in Morrowind's ruling political...","fid":"content"}]}]}