{"stem":"royal","instances":[{"docUri":"librarium\/morrowindTables%20-%20Copy.html","score":1,"contexts":[{"form":"Royal","weight":"1","pos":3300,"context":"<mark>Royal<\/mark>_Palace"}]},{"docUri":"librarium\/morrowindTables.html","score":1,"contexts":[{"form":"royal","weight":"1","pos":3316,"context":"<mark>royal<\/mark> palace","fid":"loc"}]},{"docUri":"librarium\/smugglers_island.html","score":1,"contexts":[{"form":"royal","weight":"1","pos":149,"context":"...the mysterious figure with ties to one of the <mark>royal<\/mark> Houses, everyone except for S'Riizh and Harithoel....","fid":"content","in":["ssCtx5"]}]},{"docUri":"librarium\/the_book_of_dawn_n_dusk.html","score":1,"contexts":[{"form":"Royal","weight":"1","pos":85,"context":"<mark>Royal<\/mark> Palace: Visitable? yes","fid":"acq"}]}]}