{"stem":"sergeant","instances":[{"docUri":"librarium\/For_my_Gods_and_Emperor.html","score":3,"contexts":[{"form":"sergeant","weight":"1","pos":555,"context":" A shrine <mark>sergeant<\/mark> helps keep order at the shrines, carries messages...","fid":"content"},{"form":"sergeants","weight":"1","pos":579,"context":"...for bold, free-spirited adventurers. Shrine <mark>sergeants<\/mark> are called upon to serve the Nine with weapon...","fid":"content"},{"form":"sergeants","weight":"1","pos":589,"context":"...weapon, armor, and spell. New shrine <mark>sergeants<\/mark> are given the easiest tasks, but later,...","fid":"content"}]}]}