{"stem":"stroke","instances":[{"docUri":"librarium\/silence.html","score":1,"contexts":[{"form":"stroke","weight":"1","pos":272,"context":"...the hall, before dispatching the battlemage with one <mark>stroke<\/mark> of his blade.","fid":"content"}]},{"docUri":"librarium\/Unnamed_Book.html","score":1,"contexts":[{"form":"stroke","weight":"1","pos":302,"context":"...then saw through the throat in three or four <mark>stroke<\/mark> rather like playing a violin. It requires little...","fid":"content"}]}]}