{"stem":"temper","instances":[{"docUri":"librarium\/Guide_to_Vvardenfell.html","score":1,"contexts":[{"form":"temperate","weight":"1","pos":201,"context":"...small farms and large plantations. The climate is <mark>temperate<\/mark> and comfortable, with moderate rainfall.","fid":"content"}]},{"docUri":"librarium\/Saryonis_Sermons_Manuscript.html","score":1,"contexts":[{"form":"temperate","weight":"1","pos":146,"context":"...speak respectfully, even of my enemies, for <mark>temperate<\/mark> words may turn aside anger.","fid":"content"}]}]}