{"stem":"tomb","instances":[{"docUri":"librarium\/morrowindTables%20-%20Copy.html","score":10,"contexts":[{"form":"Tomb","weight":"1","pos":1874,"context":"Falas Ancestral <mark>Tomb<\/mark>"},{"form":"Tomb","weight":"1","pos":2457,"context":"Indalen_Ancestral_<mark>Tomb<\/mark>"},{"form":"Tomb","weight":"1","pos":3064,"context":"Orethi Ancestral <mark>Tomb<\/mark>"},{"form":"Tomb","weight":"1","pos":3177,"context":"Ravel Ancestral <mark>Tomb<\/mark>"},{"form":"Tomb","weight":"1","pos":3530,"context":"Sarano Ancestral <mark>Tomb<\/mark>"},{"form":"Tomb","weight":"1","pos":3545,"context":"Sarys Ancestral <mark>Tomb<\/mark>"},{"form":"Tomb","weight":"1","pos":3554,"context":"Savel_Ancestral_<mark>Tomb<\/mark>"},{"form":"Tomb","weight":"1","pos":3576,"context":"Sethan_Ancestral_<mark>Tomb<\/mark>"},{"form":"Tomb","weight":"1","pos":4202,"context":"Telvayn Ancestral <mark>Tomb<\/mark>"},{"form":"Tomb","weight":"1","pos":4238,"context":"Tharys_Ancestral_<mark>Tomb<\/mark>"}]},{"docUri":"librarium\/morrowindTables.html","score":10,"contexts":[{"form":"tomb","weight":"1","pos":1892,"context":"falas ancestral <mark>tomb<\/mark>","fid":"loc"},{"form":"tomb","weight":"1","pos":2470,"context":"indalen ancestral <mark>tomb<\/mark>","fid":"loc"},{"form":"tomb","weight":"1","pos":3084,"context":"orethi ancestral <mark>tomb<\/mark>","fid":"loc"},{"form":"tomb","weight":"1","pos":3197,"context":"ravel ancestral <mark>tomb<\/mark>","fid":"loc"},{"form":"tomb","weight":"1","pos":3530,"context":"sarano ancestral <mark>tomb<\/mark>","fid":"loc"},{"form":"tomb","weight":"1","pos":3545,"context":"sarys ancestral <mark>tomb<\/mark>","fid":"loc"},{"form":"tomb","weight":"1","pos":3554,"context":"savel ancestral <mark>tomb<\/mark>","fid":"loc"},{"form":"tomb","weight":"1","pos":3576,"context":"sethan ancestral <mark>tomb<\/mark>","fid":"loc"},{"form":"tomb","weight":"1","pos":4193,"context":"telvayn ancestral <mark>tomb<\/mark>","fid":"loc"},{"form":"tomb","weight":"1","pos":4229,"context":"tharys ancestral <mark>tomb<\/mark>","fid":"loc"}]},{"docUri":"librarium\/Blasphemous_Revenants.html","score":3,"contexts":[{"form":"tomb","weight":"1","pos":127,"context":"...worlds they linger, held to the hearth and <mark>tomb<\/mark> by blood and loyalty. And if they come...","fid":"content"},{"form":"tombs","weight":"1","pos":172,"context":"...the bones of your fathers and dust of your <mark>tombs<\/mark>. He seeks to bind by power what is...","fid":"content","in":["ssCtx5"]},{"form":"tombs","weight":"1","pos":248,"context":"...shores, shall they be permitted to rob our <mark>tombs<\/mark>, to bind our kin-spirits into sorcerous...","fid":"content"}]},{"docUri":"librarium\/Book_of_Life_and_Service.html","score":2,"contexts":[{"form":"Tomb","weight":"1","pos":19,"context":"Orethi Ancestral <mark>Tomb<\/mark>: Visitable? yes","fid":"acq"},{"form":"Tomb","weight":"1","pos":29,"context":"Sarano Ancestral <mark>Tomb<\/mark>: Visitable? yes","fid":"acq"}]},{"docUri":"librarium\/Book_of_Rest_and_Endings.html","score":2,"contexts":[{"form":"Tomb","weight":"1","pos":29,"context":"Telvayn Ancestral <mark>Tomb<\/mark>: Visitable? yes","fid":"acq"},{"form":"Tomb","weight":"1","pos":34,"context":"Sarys Ancestral <mark>Tomb<\/mark>: Visitable? yes","fid":"acq"}]},{"docUri":"librarium\/life_n_service_EX.html","score":2,"contexts":[{"form":"Tomb","weight":"1","pos":29,"context":" Orethi Ancestral <mark>Tomb<\/mark>: Visitable? ","fid":"acq"},{"form":"Tomb","weight":"1","pos":33,"context":"Sarano Ancestral <mark>Tomb<\/mark>: Visitable? ","fid":"acq"}]},{"docUri":"librarium\/the_book_of_dawn_n_dusk.html","score":2,"contexts":[{"form":"Tomb","weight":"1","pos":37,"context":"Indalen Ancestral <mark>Tomb<\/mark>: Visitable? yes","fid":"acq"},{"form":"Tomb","weight":"1","pos":77,"context":"Tharys Ancestral <mark>Tomb<\/mark>: Visitable? yes","fid":"acq"}]},{"docUri":"librarium\/36_Lessons_of_Vivec_Sermon_1.html","score":1,"contexts":[{"form":"Tomb","weight":"1","pos":16,"context":"Falas Ancestral <mark>Tomb<\/mark>: Visitable? yes","fid":"acq"}]},{"docUri":"librarium\/Corpse_Preparation_v_I.html","score":1,"contexts":[{"form":"tomb","weight":"1","pos":344,"context":"...the north, through an Imperial burial in a <mark>tomb<\/mark> or city cemetery is more common in the south...","fid":"content"}]},{"docUri":"librarium\/Fellowship_of_the_Temple.html","score":1,"contexts":[{"form":"tombs","weight":"1","pos":279,"context":"...and in places of pilgrimage, and in the <mark>tombs<\/mark> of our ancestors.","fid":"content"}]},{"docUri":"librarium\/Grasping_Fortune.html","score":1,"contexts":[{"form":"Tomb","weight":"1","pos":48,"context":"Ravel Ancestral <mark>Tomb<\/mark>: Visitable? yes","fid":"acq"}]},{"docUri":"librarium\/The_Cantatas_of_Vivec.html","score":1,"contexts":[{"form":"tomb","weight":"1","pos":202,"context":"Will it take to seal this restless <mark>tomb<\/mark>?","fid":"content"}]},{"docUri":"librarium\/The_Consolations_of_Prayer.html","score":1,"contexts":[{"form":"tomb","weight":"1","pos":118,"context":"..., or at pilgrim waysides, or in the <mark>tomb<\/mark> of the sanctified.","fid":"content"}]},{"docUri":"librarium\/The_Prayers_of_Baranat.html","score":1,"contexts":[{"form":"Tomb","weight":"1","pos":23,"context":"Sethan Ancestral <mark>Tomb<\/mark>: Visitable? yes","fid":"acq"}]},{"docUri":"librarium\/Unnamed_Book.html","score":1,"contexts":[{"form":"Tomb","weight":"1","pos":21,"context":"Savel Ancestral <mark>Tomb<\/mark>: Visitable? yes","fid":"acq"}]}]}