{"stem":"tri","instances":[{"docUri":"librarium\/buyn_game_EX.html","score":2,"contexts":[{"form":"try","weight":"1","pos":122,"context":"...you are offered something for ten gold pieces, <mark>try<\/mark> offering six and see where that takes you.","fid":"content"},{"form":"try","weight":"1","pos":153,"context":"...-keeper compliments your taste, smile, but <mark>try<\/mark> to resist the flattery.","fid":"content"}]},{"docUri":"librarium\/The_Four_Suitors_of_Benitah.html","score":2,"contexts":[{"form":"trying","weight":"1","pos":127,"context":"...play he had pushed a bully away who was <mark>trying<\/mark> to hurt her, and the look of appreciation she...","fid":"content","in":["ssCtx5"]},{"form":"trying","weight":"1","pos":243,"context":"...word in with all her counselors. They are <mark>trying<\/mark> to find her a new husband, and she...","fid":"content"}]},{"docUri":"librarium\/Realizations_of_Acrobacy.html","score":1,"contexts":[{"form":"try","weight":"1","pos":454,"context":"...a good troupe, and it seemed smarter to <mark>try<\/mark> to save everyone. In any case, I...","fid":"content"}]},{"docUri":"librarium\/The_Prayers_of_Baranat.html","score":1,"contexts":[{"form":"tried","weight":"1","pos":259,"context":"...boulder which turned to dust on impact. Feryn <mark>tried<\/mark> to get to his feet, but Baranat tore...","fid":"content"}]},{"docUri":"librarium\/Unnamed_Book.html","score":1,"contexts":[{"form":"trying","weight":"1","pos":124,"context":"...you'd like us to do?\" asked Galsiah calmly, <mark>trying<\/mark> to keep the tone of the group down. Most...","fid":"content"}]}]}