{"stem":"wait","instances":[{"docUri":"librarium\/Unnamed_Book.html","score":3,"contexts":[{"form":"waiting","weight":"1","pos":595,"context":"...the labyrinthine tunnels of sludge. His guar was <mark>waiting<\/mark> where he left it at the city gates,...","fid":"content"},{"form":"wait","weight":"1","pos":703,"context":"...order a meal -- a big one -- and <mark>wait<\/mark>. Hours would pass, and so would their...","fid":"content"},{"form":"waiting","weight":"1","pos":822,"context":"...Boethiah. He lay still in his bed, <mark>waiting<\/mark>, but there was no sound except the usual...","fid":"content"}]},{"docUri":"librarium\/36_Lessons_of_Vivec_Sermon_1.html","score":1,"contexts":[{"form":"wait","weight":"1","pos":199,"context":"'Whom do you <mark>wait<\/mark> for?'","fid":"content"}]},{"docUri":"librarium\/Arkay_the_Enemy.html","score":1,"contexts":[{"form":"Wait","weight":"1","pos":132,"context":"To the Hidden: <mark>Wait<\/mark>, as always, in the darkness.","fid":"content"}]}]}