{"stem":"wood","instances":[{"docUri":"librarium\/morrowindTables%20-%20Copy.html","score":4,"contexts":[{"form":"Wood","weight":"1","pos":77,"context":"No-h's Picture Book of <mark>Wood<\/mark>","fid":"nav"},{"form":"Wood","weight":"1","pos":792,"context":"No-h's Picture Book of <mark>Wood<\/mark>, count: 1"},{"form":"Wood","weight":"1","pos":1894,"context":"No-h's Picture Book of <mark>Wood<\/mark>, count: 1"},{"form":"Wood","weight":"1","pos":5438,"context":"<mark>Wood<\/mark> Elves"}]},{"docUri":"librarium\/morrowindTables.html","score":4,"contexts":[{"form":"Wood","weight":"1","pos":101,"context":"No-h's Picture Book of <mark>Wood<\/mark>"},{"form":"Wood","weight":"1","pos":816,"context":"No-h's Picture Book of <mark>Wood<\/mark>, count: 1","fid":"loc"},{"form":"Wood","weight":"1","pos":1912,"context":"No-h's Picture Book of <mark>Wood<\/mark>, count: 1","fid":"loc"},{"form":"wood","weight":"1","pos":5493,"context":"<mark>wood<\/mark> elves","fid":"group"}]},{"docUri":"librarium\/No'hs_Picture_Book_of_Wood.html","score":4,"contexts":[{"form":"Wood","weight":"2","pos":12,"context":"No-h's Picture Book of <mark>Wood<\/mark>","fid":"content"},{"form":"Wood","weight":"1","pos":23,"context":"<mark>Wood<\/mark> is pretty","fid":"content"},{"form":"Wood","weight":"1","pos":25,"context":"<mark>Wood<\/mark> is nice","fid":"content"}]},{"docUri":"librarium\/im_my_own_grandpa.html","score":1,"contexts":[{"form":"Wood","weight":"1","pos":48,"context":"If a <mark>Wood<\/mark> Elf mime falls in a forest, who cares...","fid":"content"}]},{"docUri":"librarium\/special_Flora_of_Tamriel.html","score":1,"contexts":[{"form":"wood","weight":"1","pos":237,"context":"...grow deep in the forests of Skyrim. The <mark>wood<\/mark> from these trees is as hard as the metal...","fid":"content"}]}]}