{"stem":"worst","instances":[{"docUri":"librarium\/Corpse_Preparation_v_I.html","score":1,"contexts":[{"form":"worst","weight":"1","pos":235,"context":"...other race caught in Summerset Isle can expect the <mark>worst<\/mark> possible punishments.","fid":"content"}]},{"docUri":"librarium\/Guide_to_Vvardenfell.html","score":1,"contexts":[{"form":"worst","weight":"1","pos":912,"context":"...but few others venture into this region. The <mark>worst<\/mark> part of Molag Amur, called the Great Scathes...","fid":"content"}]},{"docUri":"librarium\/starlovers_log.html","score":1,"contexts":[{"form":"worst","weight":"1","pos":51,"context":"...and soldiers for this holdout. I fear the <mark>worst<\/mark>.\"","fid":"content","in":["ssCtx5"]}]}]}